PyViCare/Feature.py
PyViCare/PyViCare.py
PyViCare/PyViCareAbstractOAuthManager.py
PyViCare/PyViCareBrowserOAuthManager.py
PyViCare/PyViCareCachedService.py
PyViCare/PyViCareDevice.py
PyViCare/PyViCareDeviceConfig.py
PyViCare/PyViCareElectricalEnergySystem.py
PyViCare/PyViCareFloorHeating.py
PyViCare/PyViCareFuelCell.py
PyViCare/PyViCareGateway.py
PyViCare/PyViCareGazBoiler.py
PyViCare/PyViCareHeatCurveCalculation.py
PyViCare/PyViCareHeatPump.py
PyViCare/PyViCareHeatingDevice.py
PyViCare/PyViCareHybrid.py
PyViCare/PyViCareOAuthManager.py
PyViCare/PyViCareOilBoiler.py
PyViCare/PyViCarePelletsBoiler.py
PyViCare/PyViCareRadiatorActuator.py
PyViCare/PyViCareRepeater.py
PyViCare/PyViCareRoomSensor.py
PyViCare/PyViCareService.py
PyViCare/PyViCareUtils.py
PyViCare/PyViCareVentilationDevice.py
PyViCare/__init__.py
pyvicare-2.56.0.dist-info/METADATA
pyvicare-2.56.0.dist-info/WHEEL
pyvicare-2.56.0.dist-info/licenses/LICENSE
pyvicare-2.56.0.dist-info/RECORD
