Metadata-Version: 2.4
Name: PyViCare
Version: 2.56.0
Summary: Library to communicate with the Viessmann ViCare API.
License: Apache-2.0
License-File: LICENSE
Keywords: viessmann,vicare,api
Author: Simon Gillet
Author-email: mail+pyvicare@gillet.ninja
Maintainer: Christopher Fenner
Maintainer-email: fenner.christopher@gmail.com
Requires-Python: >=3.10,<4.0
Classifier: Intended Audience :: Developers
Classifier: License :: OSI Approved :: Apache Software License
Classifier: Natural Language :: English
Classifier: Operating System :: OS Independent
Classifier: Programming Language :: Python :: 3
Classifier: Programming Language :: Python :: 3.10
Classifier: Programming Language :: Python :: 3.11
Classifier: Programming Language :: Python :: 3.12
Classifier: Programming Language :: Python :: 3.13
Classifier: Programming Language :: Python :: 3.14
Classifier: Topic :: Software Development :: Libraries :: Python Modules
Requires-Dist: authlib (>1.2.0)
Requires-Dist: deprecated (>=1.2.15,<2.0.0)
Requires-Dist: requests (>=2.31.0)
Project-URL: Bug Tracker, https://github.com/openviess/PyViCare/issues
Project-URL: Changelog, https://github.com/openviess/PyViCare/releases
Project-URL: Documentation, https://github.com/openviess/PyViCare
Project-URL: Homepage, https://github.com/openviess/PyViCare
Project-URL: Repository, https://github.com/openviess/PyViCare
